mason_image/__init__.py
mason_image/converter.py
mason_image-0.1.4.dist-info/LICENSE
mason_image-0.1.4.dist-info/METADATA
mason_image-0.1.4.dist-info/WHEEL
mason_image-0.1.4.dist-info/entry_points.txt
mason_image-0.1.4.dist-info/top_level.txt
mason_image-0.1.4.dist-info/RECORD
