Metadata-Version: 2.1
Name: mason-image
Version: 0.1.4
Summary: mess up a image
Home-page: https://github.com/Mason-Lin/mason_image
Author: Mason Lin
Author-email: pizza0117@gmail.com
License: UNKNOWN
Platform: UNKNOWN
Classifier: Programming Language :: Python :: 3
Classifier: License :: OSI Approved :: MIT License
Classifier: Operating System :: OS Independent
Requires-Dist: Pillow (>=5.1.0)
